setup.py
NAME/__init__.py
NAME/distributing_test.py
distributing_test.egg-info/PKG-INFO
distributing_test.egg-info/SOURCES.txt
distributing_test.egg-info/dependency_links.txt
distributing_test.egg-info/requires.txt
distributing_test.egg-info/top_level.txt