Metadata-Version: 1.0
Name: distributing-test
Version: 0.1
Summary: Just testing some stuff
Home-page: UNKNOWN
Author: Thomas B.
Author-email: UNKNOWN
License: UNKNOWN
Platform: UNKNOWN
